aws_assumptions/__init__.py
aws_assumptions/identity.py
aws_assumptions/scripts.py
aws_assumptions-0.2.2.dist-info/WHEEL
aws_assumptions-0.2.2.dist-info/entry_points.txt
aws_assumptions-0.2.2.dist-info/METADATA
aws_assumptions-0.2.2.dist-info/RECORD
