Metadata-Version: 2.1
Name: aws-assumptions
Version: 0.2.2
Summary: Assume role(s) from a terminal and easily manage boto3 clients for multiple identities at once.
Home-page: https://github.com/mathewmoon/aws-assumptions
Author: Mathew Moon
Author-email: me@mathewmoon.net
Requires-Python: >=3.9,<4.0
Classifier: Programming Language :: Python :: 3
Classifier: Programming Language :: Python :: 3.9
Classifier: Programming Language :: Python :: 3.10
Classifier: Programming Language :: Python :: 3.11
Requires-Dist: boto3 (>=1.26)
Requires-Dist: python-dotenv (>=1.0.0,<2.0.0)
Project-URL: Documentation, https://github.com/mathewmoon/aws-assumptions
